weather_in/__init__.py
weather_in/cli.py
weather_in/weather_in.py
weather_in-1.1.5.dist-info/LICENSE
weather_in-1.1.5.dist-info/METADATA
weather_in-1.1.5.dist-info/WHEEL
weather_in-1.1.5.dist-info/entry_points.txt
weather_in-1.1.5.dist-info/top_level.txt
weather_in-1.1.5.dist-info/RECORD
