Metadata-Version: 2.1
Name: weather-in
Version: 1.1.5
Summary: OpenWeather CLI script
Home-page: https://github.com/fleetyeets/weather.in
Author: Travis Pawlikowski
Author-email: tnp123@protonmail.com
License: UNKNOWN
Project-URL: Bug Reports, https://github.com/fleetyeets/weather.in/issues
Project-URL: Source, https://github.com/fleetyeets/weather.in
Platform: UNKNOWN
Classifier: Programming Language :: Python :: 3
Classifier: Development Status :: 5 - Production/Stable
Classifier: License :: OSI Approved :: GNU General Public License v3 (GPLv3)
Classifier: Operating System :: OS Independent
Requires-Python: >=3.0
License-File: LICENSE
